LICENSE
MANIFEST.in
README.rst
setup.py
sentry_geo/__init__.py
sentry_geo/interfaces.py
sentry_geo/plugin.py
sentry_geo.egg-info/PKG-INFO
sentry_geo.egg-info/SOURCES.txt
sentry_geo.egg-info/dependency_links.txt
sentry_geo.egg-info/entry_points.txt
sentry_geo.egg-info/not-zip-safe
sentry_geo.egg-info/requires.txt
sentry_geo.egg-info/top_level.txt
sentry_geo/static/openlayers/OpenLayers.js
sentry_geo/static/openlayers/OpenLayers.light.js
sentry_geo/static/openlayers/img/blank.gif
sentry_geo/static/openlayers/img/cloud-popup-relative.png
sentry_geo/static/openlayers/img/drag-rectangle-off.png
sentry_geo/static/openlayers/img/drag-rectangle-on.png
sentry_geo/static/openlayers/img/east-mini.png
sentry_geo/static/openlayers/img/layer-switcher-maximize.png
sentry_geo/static/openlayers/img/layer-switcher-minimize.png
sentry_geo/static/openlayers/img/marker-blue.png
sentry_geo/static/openlayers/img/marker-gold.png
sentry_geo/static/openlayers/img/marker-green.png
sentry_geo/static/openlayers/img/marker.png
sentry_geo/static/openlayers/img/measuring-stick-off.png
sentry_geo/static/openlayers/img/measuring-stick-on.png
sentry_geo/static/openlayers/img/north-mini.png
sentry_geo/static/openlayers/img/panning-hand-off.png
sentry_geo/static/openlayers/img/panning-hand-on.png
sentry_geo/static/openlayers/img/slider.png
sentry_geo/static/openlayers/img/south-mini.png
sentry_geo/static/openlayers/img/west-mini.png
sentry_geo/static/openlayers/img/zoom-minus-mini.png
sentry_geo/static/openlayers/img/zoom-plus-mini.png
sentry_geo/static/openlayers/img/zoom-world-mini.png
sentry_geo/static/openlayers/img/zoombar.png
sentry_geo/static/openlayers/theme/default/google.css
sentry_geo/static/openlayers/theme/default/google.tidy.css
sentry_geo/static/openlayers/theme/default/ie6-style.css
sentry_geo/static/openlayers/theme/default/ie6-style.tidy.css
sentry_geo/static/openlayers/theme/default/style.css
sentry_geo/static/openlayers/theme/default/style.mobile.css
sentry_geo/static/openlayers/theme/default/style.mobile.tidy.css
sentry_geo/static/openlayers/theme/default/style.tidy.css
sentry_geo/static/openlayers/theme/default/img/add_point_off.png
sentry_geo/static/openlayers/theme/default/img/add_point_on.png
