Metadata-Version: 1.1
Name: sentry-geo
Version: 0.0.0
Summary: A Sentry plugin that adds support for geo data.
Home-page: http://github.com/faulkner/sentry-geo
Author: Chris Faulkner
Author-email: thefaulkner@gmail.com
License: Copyright (c) 2012, Chris Faulkner
